{
  "title": "iste adipisci totam eveniet eveniet",
  "subtitle": "ipsam consequatur dolore cupiditate laborum nostrum ut recusandae laudantium consectetur dolor voluptatibus doloremque voluptatem",
  "content": "error at omnis molestias fugiat quod cum a consequuntur hic ducimus eius dicta atque beatae maiores quae optio ducimus dignissimos neque cumque totam vero fuga possimus explicabo occaecati dolorum praesentium officiis aperiam exercitationem error est aliquid impedit commodi laudantium repudiandae veniam repellendus repellat error dolorem impedit nam dolore necessitatibus quaerat cumque reiciendis porro natus reprehenderit sequi quisquam asperiores ut dolorum doloremque ipsa veritatis sit in dicta porro quam molestias illum est consectetur quis similique facilis repellat voluptatum cum omnis rerum voluptatibus sint facilis ratione recusandae consequuntur sunt hic itaque hic minus architecto similique optio itaque ut non quibusdam repudiandae architecto tempora nobis eos sint mollitia consequatur quis repellendus optio voluptates similique quisquam quaerat odit nam alias esse facere corporis quisquam voluptatibus at soluta temporibus voluptate vel voluptatibus architecto magnam consequuntur assumenda aperiam aut nam sequi cumque consequuntur expedita rem amet vero enim dolores",
  "id": 86,
  "created_at": "2022-05-12T14:59:13.691Z"
}